pypaTest/setup.py
pypaTest-0.0.0.2.dist-info/METADATA
pypaTest-0.0.0.2.dist-info/WHEEL
pypaTest-0.0.0.2.dist-info/top_level.txt
pypaTest-0.0.0.2.dist-info/RECORD
