Metadata-Version: 2.1
Name: pypaTest
Version: 0.0.0.2
Summary: First Test Package
Home-page: https://github.com/Secludor/
Author: secludor
Author-email: caelumator@gmail.com
License: MIT
Requires-Python: >=3
